skvai/__init__.py
skvai/__main__.py
skvai/cli.py
skvai/core.py
skvai/data_loader.py
skvai/tasks/__init__.py
skvai/tasks/classification.py
skvai/tasks/clustering.py
skvai/tasks/regression.py
skvai/utils/__init__.py
skvai/utils/data_loader.py
skvai-0.1.0.dist-info/licenses/LICENSE
tests/__init__.py
tests/test_classification_task.py
tests/test_data_loader.py
tests/test_imports.py
skvai-0.1.0.dist-info/METADATA
skvai-0.1.0.dist-info/WHEEL
skvai-0.1.0.dist-info/top_level.txt
skvai-0.1.0.dist-info/RECORD
